compnal/base_compnal.cpython-311-darwin.so
compnal/_version.py
compnal/__init__.py
compnal/solver/__init__.py
compnal/solver/result.py
compnal/solver/parameters.py
compnal/solver/cmc.py
compnal/solver/__pycache__/parameters.cpython-311.opt-1.pyc
compnal/solver/__pycache__/result.cpython-311.pyc
compnal/solver/__pycache__/parameters.cpython-311.pyc
compnal/solver/__pycache__/cmc.cpython-311.pyc
compnal/solver/__pycache__/cmc.cpython-311.opt-1.pyc
compnal/solver/__pycache__/result.cpython-311.opt-1.pyc
compnal/solver/__pycache__/__init__.cpython-311.opt-1.pyc
compnal/solver/__pycache__/__init__.cpython-311.pyc
compnal/__pycache__/_version.cpython-311.opt-1.pyc
compnal/__pycache__/_version.cpython-311.pyc
compnal/__pycache__/__init__.cpython-311.opt-1.pyc
compnal/__pycache__/__init__.cpython-311.pyc
compnal/.dylibs/libomp.dylib
compnal/lattice/cubic.py
compnal/lattice/chain.py
compnal/lattice/boundary_condition.py
compnal/lattice/__init__.py
compnal/lattice/lattice_info.py
compnal/lattice/infinite_range.py
compnal/lattice/square.py
compnal/lattice/__pycache__/square.cpython-311.opt-1.pyc
compnal/lattice/__pycache__/boundary_condition.cpython-311.opt-1.pyc
compnal/lattice/__pycache__/infinite_range.cpython-311.pyc
compnal/lattice/__pycache__/lattice_info.cpython-311.pyc
compnal/lattice/__pycache__/cubic.cpython-311.opt-1.pyc
compnal/lattice/__pycache__/square.cpython-311.pyc
compnal/lattice/__pycache__/lattice_info.cpython-311.opt-1.pyc
compnal/lattice/__pycache__/cubic.cpython-311.pyc
compnal/lattice/__pycache__/chain.cpython-311.opt-1.pyc
compnal/lattice/__pycache__/chain.cpython-311.pyc
compnal/lattice/__pycache__/__init__.cpython-311.opt-1.pyc
compnal/lattice/__pycache__/boundary_condition.cpython-311.pyc
compnal/lattice/__pycache__/infinite_range.cpython-311.opt-1.pyc
compnal/lattice/__pycache__/__init__.cpython-311.pyc
compnal/model/__init__.py
compnal/model/__pycache__/__init__.cpython-311.opt-1.pyc
compnal-0.0.14.dist-info/RECORD
compnal-0.0.14.dist-info/LICENSE
compnal-0.0.14.dist-info/WHEEL
compnal-0.0.14.dist-info/top_level.txt
compnal-0.0.14.dist-info/METADATA
