Metadata-Version: 2.1
Name: compnal
Version: 0.0.14
Summary: Condensed Matter Physics Numerical Analytics Libirary
Author: Kohei Suzuki
License: Apache License 2.0
Project-URL: Source, https://github.com/K-Suzuki-Jij/compnal
Classifier: License :: OSI Approved :: Apache Software License
Classifier: Intended Audience :: Science/Research
Classifier: Programming Language :: Python :: 3.9
Classifier: Programming Language :: Python :: 3.10
Classifier: Programming Language :: Python :: 3.11
Classifier: Programming Language :: Python :: 3.12
Classifier: Operating System :: POSIX
Classifier: Operating System :: Unix
Classifier: Operating System :: MacOS
Requires-Python: <3.13,>=3.9
License-File: LICENSE
Requires-Dist: numpy <1.27.0
Requires-Dist: psutil
Requires-Dist: h5py
